gwill/__init__.py
gwill/changes/BChanges.py
gwill/changes/DrawGossip.py
gwill/changes/__init__.py
gwill/conf/GuaCi.py
gwill/conf/__init__.py
gwill/data/__init__.py
gwill/data/gua_ci/__init__.py
gwill/data/gua_ci/gwill_solution.py
gwill/data/gua_ci/i_000000
gwill/data/gua_ci/i_000001
gwill/data/gua_ci/i_000010
gwill/data/gua_ci/i_000011
gwill/data/gua_ci/i_000100
gwill/data/gua_ci/i_000101
gwill/data/gua_ci/i_000110
gwill/data/gua_ci/i_000111
gwill/data/gua_ci/i_001000
gwill/data/gua_ci/i_001001
gwill/data/gua_ci/i_001010
gwill/data/gua_ci/i_001011
gwill/data/gua_ci/i_001100
gwill/data/gua_ci/i_001101
gwill/data/gua_ci/i_001110
gwill/data/gua_ci/i_001111
gwill/data/gua_ci/i_010000
gwill/data/gua_ci/i_010001
gwill/data/gua_ci/i_010010
gwill/data/gua_ci/i_010011
gwill/data/gua_ci/i_010100
gwill/data/gua_ci/i_010101
gwill/data/gua_ci/i_010110
gwill/data/gua_ci/i_010111
gwill/data/gua_ci/i_011000
gwill/data/gua_ci/i_011001
gwill/data/gua_ci/i_011010
gwill/data/gua_ci/i_011011
gwill/data/gua_ci/i_011100
gwill/data/gua_ci/i_011101
gwill/data/gua_ci/i_011110
gwill/data/gua_ci/i_011111
gwill/data/gua_ci/i_100000
gwill/data/gua_ci/i_100001
gwill/data/gua_ci/i_100010
gwill/data/gua_ci/i_100011
gwill/data/gua_ci/i_100100
gwill/data/gua_ci/i_100101
gwill/data/gua_ci/i_100110
gwill/data/gua_ci/i_100111
gwill/data/gua_ci/i_101000
gwill/data/gua_ci/i_101001
gwill/data/gua_ci/i_101010
gwill/data/gua_ci/i_101011
gwill/data/gua_ci/i_101100
gwill/data/gua_ci/i_101101
gwill/data/gua_ci/i_101110
gwill/data/gua_ci/i_101111
gwill/data/gua_ci/i_110000
gwill/data/gua_ci/i_110001
gwill/data/gua_ci/i_110010
gwill/data/gua_ci/i_110011
gwill/data/gua_ci/i_110100
gwill/data/gua_ci/i_110101
gwill/data/gua_ci/i_110110
gwill/data/gua_ci/i_110111
gwill/data/gua_ci/i_111000
gwill/data/gua_ci/i_111001
gwill/data/gua_ci/i_111010
gwill/data/gua_ci/i_111011
gwill/data/gua_ci/i_111100
gwill/data/gua_ci/i_111101
gwill/data/gua_ci/i_111110
gwill/data/gua_ci/i_111111
godwill-1.0.0.dist-info/LICENSE
godwill-1.0.0.dist-info/METADATA
godwill-1.0.0.dist-info/WHEEL
godwill-1.0.0.dist-info/entry_points.txt
godwill-1.0.0.dist-info/top_level.txt
godwill-1.0.0.dist-info/zip-safe
godwill-1.0.0.dist-info/RECORD
