Metadata-Version: 2.1
Name: godwill
Version: 1.0.0
Summary: 周易64卦
Home-page: https://github.com/rockyCheung/godwill.git
Author: Rocky
Author-email: 274935730@qq.com
License: PSF
Platform: UNKNOWN
Classifier: License :: OSI Approved :: MIT License
Classifier: Programming Language :: Python
Classifier: Intended Audience :: Developers
Classifier: Operating System :: OS Independent
Classifier: Programming Language :: Python :: 3
Classifier: Programming Language :: Python :: 3.3
Classifier: Programming Language :: Python :: 3.4
Classifier: Programming Language :: Python :: 3.5
Classifier: Programming Language :: Python :: 3.6
Classifier: Programming Language :: Python :: 3.7
Classifier: Programming Language :: Python :: 3 :: Only
Requires-Python: >=3
Requires-Dist: pytest (>=4.3.1)
Requires-Dist: readme-renderer (>=21.0)
